netdog-0.1.10.dist-info/METADATA
netdog-0.1.10.dist-info/WHEEL
netdog-0.1.10.dist-info/entry_points.txt
netdog-0.1.10.dist-info/licenses/LICENSE
netdog/__init__.py
netdog/cli.py
netdog/netdogif.py
netdog-0.1.10.dist-info/RECORD
