Metadata-Version: 2.1
Name: netdog
Version: 0.1.10
Summary: It is like netcat implemented in python.
Author-Email: vz-shark <vz-shark@miraikanai.net>
License: MIT
Classifier: Programming Language :: Python :: 3
Classifier: License :: OSI Approved :: MIT License
Classifier: Operating System :: OS Independent
Project-URL: Homepage, https://github.com/vz-shark/netdog
Project-URL: Issues, https://github.com/vz-shark/netdog/issues
Requires-Python: <3.13,>=3.12
Requires-Dist: termcolor>=2.5.0
